btlm/__init__.py
btlm/pytransform/__init__.py
btlm/pytransform/platforms/linux/aarch64/_pytransform.so
btlm/pytransform/platforms/linux/x86_64/_pytransform.so
btlm-0.0.6.dist-info/LICENSE.txt
btlm-0.0.6.dist-info/METADATA
btlm-0.0.6.dist-info/WHEEL
btlm-0.0.6.dist-info/top_level.txt
btlm-0.0.6.dist-info/RECORD
